<?xml version="1.0" encoding="UTF-8" standalone="yes"?>
<servico xsi:schemaLocation="http://servicos.gov.br/v3/schema.../servico.xsd" xmlns="http://servicos.gov.br/v3/schema" xmlns:xsi="http://www.w3.org/2001/XMLSchema-instance">
    <id>seguranca1</id>
    <dbId>1060</dbId>
    <nome>Segurança1</nome>
    <sigla></sigla>
    <descricao>Ter segurança</descricao>
    <contato></contato>
    <gratuito>true</gratuito>
    <porcentagem-manual>false</porcentagem-manual>
    <servico-digital>false</servico-digital>
    <link-servico-digital></link-servico-digital>
    <solicitantes>
        <solicitante id="809">
            <tipo>Cidadãos</tipo>
            <requisitos></requisitos>
        </solicitante>
    </solicitantes>
    <tempo-total-estimado>
        <nao-estimado-ainda/>
        <descricao></descricao>
    </tempo-total-estimado>
    <validade-documento>
        <descricao></descricao>
    </validade-documento>
    <etapas>
        <etapa id="1996">
            <titulo>Pedir</titulo>
            <descricao></descricao>
            <documentos>
                <default/>
            </documentos>
            <custos>
                <default/>
            </custos>
            <canais-de-prestacao>
                <default>
                    <canal-de-prestacao id="2023" tipo="presencial">
                        <descricao>No órgão</descricao>
                    </canal-de-prestacao>
                </default>
            </canais-de-prestacao>
        </etapa>
    </etapas>
    <orgao id="http://estruturaorganizacional.dados.gov.br/id/unidade-organizacional/316" dbId="37532">
        <nomeOrgao>Ministério da Justiça  (MJ)</nomeOrgao>
    </orgao>
    <segmentos-da-sociedade>
        <item idSegmento="1" idServicoSegmento="2318">Cidadãos</item>
    </segmentos-da-sociedade>
    <areas-de-interesse>
        <item>Segurança, justiça e polícia</item>
    </areas-de-interesse>
    <palavras-chave>
        <item id="2423">segurança</item>
        <item id="2424">justiça</item>
        <item id="2425">polícia</item>
    </palavras-chave>
</servico>
