<?xml version="1.0" encoding="UTF-8" standalone="yes"?>
<pagina-tematica >
    <conteudo>&lt;div style="text-align:center;font-size:200%"&gt;
&lt;p style="color:#06acff"&gt;Obrigado por avaliar o nosso Portal!&lt;/p&gt;
&lt;p color="#06acff"&gt;Ficamos felizes que você tenha gostado.&lt;/p&gt;
&lt;p color="#06acff"&gt;Volte sempre!&lt;/p&gt;
&lt;/div&gt;</conteudo>
    <dbId>813</dbId>
    <nome>Obrigado pela sua avaliação</nome>
    <orgaos>
        <orgao id="2981" dbId="37545">
            <nomeOrgao>Ministério do Planejamento, Desenvolvimento e Gestão (MP)</nomeOrgao>
        </orgao>
    </orgaos>
</pagina-tematica>
